agentswarm/__init__.py
agentswarm/agents/__init__.py
agentswarm/agents/base_agent.py
agentswarm/agents/gathering_agent.py
agentswarm/agents/map_reduce_agent.py
agentswarm/agents/mcp_agent.py
agentswarm/agents/merge_agent.py
agentswarm/agents/react_agent.py
agentswarm/agents/thinking_agent.py
agentswarm/agents/transformer_agent.py
agentswarm/datamodels/__init__.py
agentswarm/datamodels/context.py
agentswarm/datamodels/local_store.py
agentswarm/datamodels/message.py
agentswarm/datamodels/responses.py
agentswarm/datamodels/store.py
agentswarm/llms/__init__.py
agentswarm/llms/gemini.py
agentswarm/llms/llm.py
agentswarm/utils/__init__.py
agentswarm/utils/trace_view.py
agentswarm/utils/tracing.py
ai_agentswarm-0.1.1.dist-info/licenses/LICENSE
ai_agentswarm-0.1.1.dist-info/METADATA
ai_agentswarm-0.1.1.dist-info/WHEEL
ai_agentswarm-0.1.1.dist-info/top_level.txt
ai_agentswarm-0.1.1.dist-info/RECORD
