Metadata-Version: 2.4
Name: ai-agentswarm
Version: 0.1.1
Summary: A recursive, functional, and state-isolated Multi-Agent Framework.
Author-email: Lucas Roverelli <lucas.roverelli@gmail.com>
License: MIT License
Project-URL: Homepage, https://github.com/ai-agentswarm/agentswarm
Project-URL: Bug Tracker, https://github.com/ai-agentswarm/agentswarm/issues
Project-URL: Documentation, https://github.com/ai-agentswarm/agentswarm#readme
Keywords: ai,agents,llm,framework,recursive,react
Classifier: Development Status :: 3 - Alpha
Classifier: Intended Audience :: Developers
Classifier: License :: OSI Approved :: MIT License
Classifier: Programming Language :: Python :: 3
Classifier: Programming Language :: Python :: 3.10
Classifier: Programming Language :: Python :: 3.11
Classifier: Topic :: Software Development :: Libraries :: Application Frameworks
Classifier: Topic :: Scientific/Engineering :: Artificial Intelligence
Requires-Python: >=3.10
License-File: LICENSE
Requires-Dist: pydantic>=2.12.4
Requires-Dist: google-genai>=1.50.1
Requires-Dist: mcp
Provides-Extra: dev
Requires-Dist: pytest; extra == "dev"
Requires-Dist: twine; extra == "dev"
Requires-Dist: build; extra == "dev"
Requires-Dist: black; extra == "dev"
Requires-Dist: isort; extra == "dev"
Provides-Extra: examples
Requires-Dist: httpx; extra == "examples"
Requires-Dist: python-dotenv; extra == "examples"
Provides-Extra: docs
Requires-Dist: mkdocs; extra == "docs"
Requires-Dist: mkdocs-material; extra == "docs"
Requires-Dist: mkdocstrings[python]; extra == "docs"
Dynamic: license-file
